likability/LikabilityAnalyzer.py
likability/__init__.py
likability/findSentiment.py
likability/getTweets.py
likability/test_script.py
likability/twitterAPI.py
likability/twitterKeys.py
lykability/LikabilityAnalyzer.py
lykability/__init__.py
lykability/findSentiment.py
lykability/getTweets.py
lykability/twitterAPI.py
lykability/twitterKeys.py
lykability-1.0.0.dist-info/DESCRIPTION.rst
lykability-1.0.0.dist-info/METADATA
lykability-1.0.0.dist-info/RECORD
lykability-1.0.0.dist-info/WHEEL
lykability-1.0.0.dist-info/metadata.json
lykability-1.0.0.dist-info/top_level.txt
