Metadata-Version: 2.0
Name: lykability
Version: 1.0.0
Summary: Using empythy to score likability based on sentiment analysis of recent tweets about a given person
Home-page: https://github.com/robertjkeck2/lykability
Author: John Keck
Author-email: robertjkeck2@gmail.com
License: MIT
Keywords: machine learning,data science,NLP,natural language processing,sentiment,sentiment analysis,sentiment prediction,twitter corpus,twitter,tweets corpus,movie reviews corpus,NLTK,automated machine learning
Platform: UNKNOWN
Classifier: Development Status :: 4 - Beta
Classifier: Intended Audience :: Developers
Classifier: Topic :: Scientific/Engineering :: Artificial Intelligence
Classifier: License :: OSI Approved :: MIT License
Classifier: Programming Language :: Python :: 3
Classifier: Programming Language :: Python :: 3.5
Requires-Dist: empythy
Requires-Dist: nltk
Requires-Dist: numpy
Requires-Dist: pandas
Requires-Dist: scikit-learn
Requires-Dist: tweepy
